  1           0 LOAD_CONST               0 ('code in this script adapted from cpython/Lib/test/test_decorators.py')
              3 STORE_NAME               0 (__doc__)

  3           6 LOAD_CONST               1 (<code object funcattrs at 0x7f53c1f82830, file "cpy_test_decorators.py", line 3>)
              9 MAKE_FUNCTION            0
             12 STORE_NAME               1 (funcattrs)

 10          15 LOAD_CONST               2 ('MiscDecorators')
             18 LOAD_CONST              15 (())
             21 LOAD_CONST               3 (<code object MiscDecorators at 0x7f53c1f829b0, file "cpy_test_decorators.py", line 10>)
             24 MAKE_FUNCTION            0
             27 CALL_FUNCTION            0
             30 BUILD_CLASS         
             31 STORE_NAME               2 (MiscDecorators)

 18          34 LOAD_CONST               4 (<code object memoize at 0x7f53c1f82ab0, file "cpy_test_decorators.py", line 18>)
             37 MAKE_FUNCTION            0
             40 STORE_NAME               3 (memoize)

 33          43 LOAD_CONST               5 (<code object countcalls at 0x7f53c1f82cb0, file "cpy_test_decorators.py", line 33>)
             46 MAKE_FUNCTION            0
             49 STORE_NAME               4 (countcalls)

 45          52 LOAD_CONST               6 (<code object noteargs at 0x7f53c1f82db0, file "cpy_test_decorators.py", line 45>)
             55 MAKE_FUNCTION            0
             58 STORE_NAME               5 (noteargs)

 51          61 LOAD_CONST               7 (<code object foo at 0x7f53c1f82e30, file "cpy_test_decorators.py", line 51>)
             64 MAKE_FUNCTION            0
             67 STORE_NAME               6 (foo)

 54          70 LOAD_CONST               8 (<code object test_funcattrs at 0x7f53c1f82f30, file "cpy_test_decorators.py", line 54>)
             73 MAKE_FUNCTION            0
             76 STORE_NAME               7 (test_funcattrs)

 66          79 LOAD_CONST               9 (<code object test_MiscDecorators at 0x7f53c1f310b0, file "cpy_test_decorators.py", line 66>)
             82 MAKE_FUNCTION            0
             85 STORE_NAME               8 (test_MiscDecorators)

 74          88 LOAD_CONST              10 (<code object test_argforms at 0x7f53c1f312b0, file "cpy_test_decorators.py", line 74>)
             91 MAKE_FUNCTION            0
             94 STORE_NAME               9 (test_argforms)

 91          97 LOAD_CONST              11 (<code object test_countcalls at 0x7f53c1f313b0, file "cpy_test_decorators.py", line 91>)
            100 MAKE_FUNCTION            0
            103 STORE_NAME              10 (test_countcalls)

109         106 LOAD_CONST              12 (<code object test_memoize at 0x7f53c1f31530, file "cpy_test_decorators.py", line 109>)
            109 MAKE_FUNCTION            0
            112 STORE_NAME              11 (test_memoize)

133         115 LOAD_NAME               12 (__name__)
            118 LOAD_CONST              13 ('__main__')
            121 COMPARE_OP               2 (==)
            124 POP_JUMP_IF_FALSE      165

134         127 LOAD_NAME                7 (test_funcattrs)
            130 CALL_FUNCTION            0
            133 POP_TOP             

136         134 LOAD_NAME                8 (test_MiscDecorators)
            137 CALL_FUNCTION            0
            140 POP_TOP             

138         141 LOAD_NAME                9 (test_argforms)
            144 CALL_FUNCTION            0
            147 POP_TOP             

140         148 LOAD_NAME               10 (test_countcalls)
            151 CALL_FUNCTION            0
            154 POP_TOP             

142         155 LOAD_NAME               11 (test_memoize)
            158 CALL_FUNCTION            0
            161 POP_TOP             
            162 JUMP_FORWARD             0 (to 165)
        >>  165 LOAD_CONST              14 (None)
            168 RETURN_VALUE        
